{"cameraMode":{"drawMode":0,"name":"Shaded","section":"Shading Mode"},"sceneLighting":true,"audioPlay":false,"sceneViewState":{"m_AlwaysRefresh":false,"showFog":true,"showSkybox":true,"showFlares":true,"showImageEffects":true,"showParticleSystems":true,"showVisualEffectGraphs":true,"m_FxEnabled":true},"in2DMode":false,"pivot":{"x":37.40266036987305,"y":19.212778091430665,"z":72.99480438232422},"rotation":{"x":-0.013088122010231018,"y":-0.9868203997612,"z":0.13397736847400666,"w":-0.09183211624622345},"size":13.126286506652832,"orthographic":false}